sphinxcontrib_autodoc_filterparams/__init__.py
sphinxcontrib_autodoc_filterparams/filter_params.py
sphinxcontrib_autodoc_filterparams-0.0.1.dist-info/LICENSE.rst
sphinxcontrib_autodoc_filterparams-0.0.1.dist-info/METADATA
sphinxcontrib_autodoc_filterparams-0.0.1.dist-info/WHEEL
sphinxcontrib_autodoc_filterparams-0.0.1.dist-info/top_level.txt
sphinxcontrib_autodoc_filterparams-0.0.1.dist-info/zip-safe
sphinxcontrib_autodoc_filterparams-0.0.1.dist-info/RECORD
