Metadata-Version: 2.1
Name: sphinxcontrib-autodoc-filterparams
Version: 0.0.1
Summary: A sphinx extension to filter parameters from documentation
Home-page: https://github.com/erikkemperman/sphinxcontrib-autodoc-filterparams/
Author: Erik Kemperman
Author-email: erikkemperman@gmail.com
License: MIT
Keywords: sphinx,extension,filter,hide,exclude,parameter,argument
Platform: UNKNOWN
Classifier: Development Status :: 2 - Pre-Alpha
Classifier: Intended Audience :: Developers
Classifier: License :: OSI Approved :: MIT License
Classifier: Natural Language :: English
Classifier: Programming Language :: Python :: 3
Classifier: Programming Language :: Python :: 3.5
Classifier: Programming Language :: Python :: 3.6
Classifier: Programming Language :: Python :: 3.7
Requires-Dist: sphinx (>=2)
